encite-0.1.1.dist-info/METADATA
encite-0.1.1.dist-info/WHEEL
encite-0.1.1.dist-info/entry_points.txt
encite-0.1.1.dist-info/licenses/LICENSE
encite/__init__.py
encite/ner.py
encite-0.1.1.dist-info/RECORD
