Metadata-Version: 2.1
Name: encite
Version: 0.1.1
Summary: Named Entity Recognition using Claude Citations
Requires-Python: >=3.12
Requires-Dist: langchain-anthropic>=0.3.9
